anime_face_detector/__init__.py
anime_face_detector/detector.py
anime_face_detector/configs/mmdet/faster-rcnn.py
anime_face_detector/configs/mmdet/yolov3.py
anime_face_detector/configs/mmpose/hrnetv2.py
anime_face_detector-0.0.9.dist-info/LICENSE
anime_face_detector-0.0.9.dist-info/METADATA
anime_face_detector-0.0.9.dist-info/WHEEL
anime_face_detector-0.0.9.dist-info/top_level.txt
anime_face_detector-0.0.9.dist-info/RECORD
