Metadata-Version: 2.1
Name: anime-face-detector
Version: 0.0.9
Summary: Anime Face Detector using mmdet and mmpose
Home-page: https://github.com/hysts/anime-face-detector
Author: hysts
Requires-Python: >=3.7
License-File: LICENSE
Requires-Dist: mmcv-full (>=1.3.16)
Requires-Dist: mmdet (>=2.18.0)
Requires-Dist: mmpose (>=0.20.0)
Requires-Dist: numpy (>=1.21.3)
Requires-Dist: opencv-python-headless (>=4.5.4.58)
Requires-Dist: torch (>=1.10.0)
Requires-Dist: torchvision (>=0.11.1)
